Metadata-Version: 1.1
Name: mobagel-python-sdk
Version: 2.0.3
Summary: MoBagel SDK for Python.
Home-page: https://github.com/MOBAGEL/mobagel-python-sdk
Author: MoBagel
Author-email: us@mobagel.com
License: LICENSE.txt
Download-URL: https://github.com/MOBAGEL/mobagel-python-sdk/tarball/2.0.3
Platform: UNKNOWN
